pssst/__init__.py
pssst/errors.py
pssst/header.py
pssst/pssst.py
pssst-0.2.1.dist-info/LICENSE
pssst-0.2.1.dist-info/METADATA
pssst-0.2.1.dist-info/WHEEL
pssst-0.2.1.dist-info/top_level.txt
pssst-0.2.1.dist-info/RECORD
