Metadata-Version: 2.1
Name: pssst
Version: 0.2.1
Summary: Packet Security for Stateless Server Transactions
Home-page: https://github.com/nickovs/pypssst
Author: Nicko van Someren
Author-email: nicko@nicko.org
License: UNKNOWN
Keywords: pssst,security,crypto,stateless
Platform: UNKNOWN
Classifier: Development Status :: 4 - Beta
Classifier: Programming Language :: Python :: 3
Classifier: License :: OSI Approved :: Apache Software License
Classifier: Operating System :: OS Independent
Requires-Python: >=3.4
Requires-Dist: cryptography
